<annotation>
	<folder>photo</folder>
	<filename>1890.jpg</filename>
	<path>E:\insulator\photo\1890.jpg</path>
	<source>
		<database>Unknown</database>
	</source>
	<size>
		<width>5472</width>
		<height>3648</height>
		<depth>3</depth>
	</size>
	<segmented>0</segmented>
	<object>
		<name>insultor3</name>
		<pose>Unspecified</pose>
		<truncated>0</truncated>
		<difficult>0</difficult>
		<bndbox>
			<xmin>1521</xmin>
			<ymin>1407</ymin>
			<xmax>2270</xmax>
			<ymax>1676</ymax>
		</bndbox>
	</object>
</annotation>